.coveragerc
.gitignore
AUTHORS.rst
CHANGELOG.rst
LICENSE.txt
README.rst
requirements.txt
setup.cfg
setup.py
docs/Makefile
docs/authors.rst
docs/changelog.rst
docs/conf.py
docs/index.rst
docs/license.rst
docs/_static/.gitignore
src/iiab_captive_portal/__init__.py
src/iiab_captive_portal/captive_server.conf.example
src/iiab_captive_portal/skeleton.py
src/iiab_captive_portal.egg-info/PKG-INFO
src/iiab_captive_portal.egg-info/SOURCES.txt
src/iiab_captive_portal.egg-info/dependency_links.txt
src/iiab_captive_portal.egg-info/entry_points.txt
src/iiab_captive_portal.egg-info/not-zip-safe
src/iiab_captive_portal.egg-info/top_level.txt
tests/conftest.py
tests/test_skeleton.py