Metadata-Version: 1.1
Name: iiab-captive-portal
Version: 0.1
Summary: Add a short description here!
Home-page: http://...
Author: Anish Mangal
Author-email: anishmg@umich.edu
License: gpl3
Platform: any
Classifier: Development Status :: 4 - Beta
Classifier: Programming Language :: Python
